README.rst
setup.cfg
setup.py
postmen/__init__.py
postmen/jsont.py
postmen/rp2.py
postmen/rp3.py
postmen.egg-info/PKG-INFO
postmen.egg-info/SOURCES.txt
postmen.egg-info/dependency_links.txt
postmen.egg-info/requires.txt
postmen.egg-info/top_level.txt