Metadata-Version: 1.1
Name: postmen
Version: 1.0
Summary: Python SDK of Postmen API
Home-page: https://github.com/postmen/sdk-python
Author: Postmen
Author-email: support@postmen.com
License: MIT
Download-URL: https://github.com/postmen/sdk-python/tarball/1.0
Keywords: postmen api binding post mail airmail logistics shipping label rate rates
Platform: UNKNOWN
Classifier: Development Status :: 5 - Production/Stable
Classifier: Intended Audience :: Developers
Classifier: Topic :: Software Development
Classifier: License :: OSI Approved :: MIT License
Classifier: Programming Language :: Python :: 2
Classifier: Programming Language :: Python :: 2.7
Classifier: Programming Language :: Python :: 3
Classifier: Programming Language :: Python :: 3.2
Classifier: Programming Language :: Python :: 3.3
Classifier: Programming Language :: Python :: 3.4
